sdof-0.0.12.dist-info/RECORD
sdof-0.0.12.dist-info/WHEEL
sdof-0.0.12.dist-info/entry_points.txt
sdof-0.0.12.dist-info/top_level.txt
sdof-0.0.12.dist-info/METADATA
sdof-0.0.12.dist-info/licenses/LICENSE.txt
sdof/.DS_Store
sdof/_spectrum.pypy310-pp73-darwin.so
sdof/__init__.py
sdof/_integrate.pypy310-pp73-darwin.so
sdof/__main__.py
sdof/gamma/.DS_Store
sdof/gamma/CollocateScheme.m
sdof/gamma/NewmarkScheme.m
sdof/gamma/expand.tex
sdof/gamma/__init__.py
sdof/gamma/test.py
sdof/gamma/integrate.py
sdof/gamma/AverageScheme.m
sdof/gamma/symbols.py
sdof/gamma/GammaSDOF.m
sdof/gamma/test.m
sdof/gamma/wilson.py
sdof/gamma/scratch.md
sdof/gamma/gamma.py
sdof/integration/transition.py
sdof/integration/__init__.py
sdof/integration/newmark.py
sdof/integration/gssss.py
sdof/integration/duhamel.py
sdof/integration/alpha.py
sdof/integration/fourier.py
sdof/integration/butcher.py
sdof/rigid/gcim.py
sdof/rigid/.DS_Store
sdof/rigid/simo.py
sdof/rigid/util.py
sdof/rigid/__init__.py
sdof/rigid/other.py
sdof/rigid/vlv.py
sdof/rigid/README.md
sdof/rigid/cgco.py
sdof/rigid/rkmk.py
sdof/rigid/DiffMan_v2.0.tar.gz
sdof/rigid/__main__.py
sdof/rigid/rigid.py
sdof/rigid/images/image-1.png
sdof/rigid/images/image-3.png
sdof/rigid/images/image-2.png
sdof/rigid/images/image-6.png
sdof/rigid/images/image-7.png
sdof/rigid/images/image.png
sdof/rigid/images/image-5.png
sdof/rigid/images/image-4.png
sdof/rigid/DiffMan/dminit.m
sdof/rigid/DiffMan/Contents.m
sdof/rigid/DiffMan/dmversion.m
sdof/rigid/DiffMan/dmpath.m
sdof/rigid/DiffMan/field/Contents.m
sdof/rigid/DiffMan/field/@vectorfield/display.m
sdof/rigid/DiffMan/field/@vectorfield/seteqntype.m
sdof/rigid/DiffMan/field/@vectorfield/Contents.m
sdof/rigid/DiffMan/field/@vectorfield/setfm2g.m
sdof/rigid/DiffMan/field/@vectorfield/geteqntype.m
sdof/rigid/DiffMan/field/@vectorfield/getfm2g.m
sdof/rigid/DiffMan/field/@vectorfield/vectorfield.m
sdof/rigid/DiffMan/field/@vectorfield/getdomain.m
sdof/rigid/DiffMan/field/@vectorfield/setdomain.m
sdof/rigid/DiffMan/domain/Contents.m
sdof/rigid/DiffMan/domain/liegroup/Contents.m
sdof/rigid/DiffMan/domain/liegroup/@liegroup/eig.m
