Metadata-Version: 2.1
Name: sdof
Version: 0.0.12
Summary: Parallel integration of single degree-of-freedom systems.
Author-email: "Claudio M. Perez" <50180406+claudioperez@users.noreply.github.com>, Chrystal Chern <52893467+chrystalchern@users.noreply.github.com>
License: BSD 2-Clause License
Project-URL: repository, http://github.com/claudioperez/sdof
Project-URL: documentation, https://claudioperez.github.io/sdof
Keywords: dynamics,integration,seismic,earthquake-engineering
Classifier: Development Status :: 5 - Production/Stable
Classifier: Intended Audience :: Science/Research
Classifier: Intended Audience :: Developers
Classifier: License :: OSI Approved :: BSD License
Classifier: Programming Language :: C
Classifier: Programming Language :: Python
Classifier: Programming Language :: Python :: 3
Classifier: Programming Language :: Python :: 3.7
Classifier: Programming Language :: Python :: 3.8
Classifier: Programming Language :: Python :: 3.9
Classifier: Programming Language :: Python :: 3.10
Classifier: Programming Language :: Python :: 3.11
Classifier: Programming Language :: Python :: 3.12
Classifier: Programming Language :: Python :: 3 :: Only
Classifier: Programming Language :: Python :: Implementation :: CPython
Classifier: Topic :: Software Development
Classifier: Topic :: Scientific/Engineering
Classifier: Operating System :: Microsoft :: Windows
Classifier: Operating System :: POSIX
Classifier: Operating System :: Unix
Classifier: Operating System :: MacOS
License-File: LICENSE.txt
Requires-Dist: mdof
Requires-Dist: veux
Requires-Dist: numpy
Requires-Dist: quakeio
